ubiq_security_fpe/__init__.py
ubiq_security_fpe/ff1.py
ubiq_security_fpe/ff1_test.py
ubiq_security_fpe/ffx.py
ubiq_security_fpe/ffx_test.py
ubiq_security_fpe/version.py
ubiq_security_fpe-2.0.1.1.dist-info/LICENSE
ubiq_security_fpe-2.0.1.1.dist-info/METADATA
ubiq_security_fpe-2.0.1.1.dist-info/WHEEL
ubiq_security_fpe-2.0.1.1.dist-info/top_level.txt
ubiq_security_fpe-2.0.1.1.dist-info/RECORD
