Metadata-Version: 2.1
Name: ubiq-security-fpe
Version: 2.0.1.1
Summary: Python client library for format preserving encryption
Home-page: https://gitlab.com/ubiqsecurity/ubiq-fpe-python
Author: Ubiq Security, Inc.
Author-email: support@ubiqsecurity.com
License: Free To Use But Restricted
Classifier: Development Status :: 7 - Inactive
Classifier: Intended Audience :: Developers
Classifier: License :: OSI Approved :: MIT License
Classifier: Operating System :: OS Independent
Classifier: Programming Language :: Python
Classifier: Programming Language :: Python :: 3.5
Classifier: Programming Language :: Python :: 3.6
Classifier: Programming Language :: Python :: 3.7
Classifier: Programming Language :: Python :: 3.8
Classifier: Topic :: Software Development :: Libraries :: Python Modules
Classifier: Topic :: Security
Classifier: Topic :: Security :: Cryptography
Requires-Python: >=3.5
License-File: LICENSE
